LICENSE
paraml/__init__.py
paraml/parse.py
paraml-0.1.0.dist-info/LICENSE
paraml-0.1.0.dist-info/WHEEL
paraml-0.1.0.dist-info/METADATA
paraml-0.1.0.dist-info/RECORD
