Metadata-Version: 2.1
Name: paraml
Version: 0.1.0
Summary: a parameter definition language and parser - all in yaml
Home-page: https://github.com/marshall-lab/paraml
License: GPLv3
Keywords: yaml,params,parameters,config,validation
Author: mcmcgrath13
Requires-Python: >=3.6,<4.0
Classifier: License :: OSI Approved :: GNU General Public License v3 (GPLv3)
Classifier: License :: Other/Proprietary License
Classifier: Operating System :: OS Independent
Classifier: Programming Language :: Python :: 3
Classifier: Programming Language :: Python :: 3.6
Classifier: Programming Language :: Python :: 3.7
Classifier: Programming Language :: Python :: 3.8
Classifier: Programming Language :: Python :: 3.9
Classifier: Topic :: Software Development :: Libraries :: Python Modules
Classifier: Topic :: Utilities
Requires-Dist: oyaml (>=1.0,<2.0)
Project-URL: Repository, https://github.com/marshall-lab/paraml
